pyhocon/__init__.py
pyhocon/config_parser.py
pyhocon/config_tree.py
pyhocon/converter.py
pyhocon/exceptions.py
pyhocon/tool.py
pyhocon-0.3.54.dist-info/LICENSE
pyhocon-0.3.54.dist-info/METADATA
pyhocon-0.3.54.dist-info/WHEEL
pyhocon-0.3.54.dist-info/entry_points.txt
pyhocon-0.3.54.dist-info/top_level.txt
pyhocon-0.3.54.dist-info/RECORD
