Metadata-Version: 2.1
Name: pyhocon
Version: 0.3.54
Summary: HOCON parser for Python
Home-page: http://github.com/chimpler/pyhocon/
Author: Francois Dang Ngoc
Author-email: francois.dangngoc@gmail.com
License: Apache License 2.0
Keywords: hocon parser
Platform: UNKNOWN
Classifier: License :: OSI Approved :: Apache Software License
Classifier: Topic :: Software Development :: Libraries :: Python Modules
Classifier: Programming Language :: Python
Classifier: Programming Language :: Python :: 2
Classifier: Programming Language :: Python :: 2.7
Classifier: Programming Language :: Python :: 3
Classifier: Programming Language :: Python :: 3.4
Classifier: Programming Language :: Python :: 3.5
Classifier: Programming Language :: Python :: 3.6
Classifier: Programming Language :: Python :: 3.7
Provides-Extra: Duration
